asdk_plugin_compliance/__init__.py
asdk_plugin_compliance/api_registry.py
asdk_plugin_compliance/domain_apis_list.json
asdk_plugin_compliance/agraph/__init__.py
asdk_plugin_compliance/agraph/compliance/__init__.py
asdk_plugin_compliance/agraph/compliance/state/__init__.py
asdk_plugin_compliance/agraph/compliance/state/compliance_rule/__init__.py
asdk_plugin_compliance/agraph/compliance/state/compliance_rule/v1/__init__.py
asdk_plugin_compliance/agraph/compliance/state/compliance_rule/v1/ComplianceRuleAPI/__init__.py
asdk_plugin_compliance/agraph/compliance/state/compliance_rule/v1/ComplianceRuleAPI/api_client.py
asdk_plugin_compliance/agraph/compliance/state/compliance_rule/v1/ComplianceRuleAPI/api_response.py
asdk_plugin_compliance/agraph/compliance/state/compliance_rule/v1/ComplianceRuleAPI/configuration.py
asdk_plugin_compliance/agraph/compliance/state/compliance_rule/v1/ComplianceRuleAPI/exceptions.py
asdk_plugin_compliance/agraph/compliance/state/compliance_rule/v1/ComplianceRuleAPI/rest.py
asdk_plugin_compliance/agraph/compliance/state/compliance_rule/v1/ComplianceRuleAPI/swagger.json
asdk_plugin_compliance/agraph/compliance/state/compliance_rule/v1/ComplianceRuleAPI/api/__init__.py
asdk_plugin_compliance/agraph/compliance/state/compliance_rule/v1/ComplianceRuleAPI/api/default_compliance_rule_api.py
asdk_plugin_compliance/agraph/compliance/state/compliance_rule/v1/ComplianceRuleAPI/models/__init__.py
asdk_plugin_compliance/agraph/compliance/state/compliance_rule/v1/ComplianceRuleAPI/models/any.py
asdk_plugin_compliance/agraph/compliance/state/compliance_rule/v1/ComplianceRuleAPI/models/compliance_rule_api_filter_compliance_rules400_response.py
asdk_plugin_compliance/agraph/compliance/state/compliance_rule/v1/ComplianceRuleAPI/models/enums_compliance_deadline.py
asdk_plugin_compliance/agraph/compliance/state/compliance_rule/v1/ComplianceRuleAPI/models/enums_compliance_rule_label.py
asdk_plugin_compliance-2.0.0b2.dist-info/METADATA
asdk_plugin_compliance-2.0.0b2.dist-info/WHEEL
asdk_plugin_compliance-2.0.0b2.dist-info/top_level.txt
asdk_plugin_compliance-2.0.0b2.dist-info/RECORD
